{
  "name": "C_discova",
  "type": "discova",
  "pairs": [
    {
      "paper_id_A": "2789744648",
      "paper_id_B": "2950181023",
      "domain_A": "cs.GR",
      "domain_B": "cs.MA",
      "embedding_similarity": 0.954133,
      "structural_overlap": 0.129
    },
    {
      "paper_id_A": "3003152535",
      "paper_id_B": "2617415363",
      "domain_A": "cs.NA",
      "domain_B": "cs.MS",
      "embedding_similarity": 0.949913,
      "structural_overlap": 0.122
    },
    {
      "paper_id_A": "2981648169",
      "paper_id_B": "2952495822",
      "domain_A": "cs.MA",
      "domain_B": "cs.NA",
      "embedding_similarity": 0.94136,
      "structural_overlap": 0.0732
    },
    {
      "paper_id_A": "3003152535",
      "paper_id_B": "2950129161",
      "domain_A": "cs.NA",
      "domain_B": "cs.GL",
      "embedding_similarity": 0.953715,
      "structural_overlap": 0.0698
    },
    {
      "paper_id_A": "2905141912",
      "paper_id_B": "2907777862",
      "domain_A": "cs.OH",
      "domain_B": "cs.GL",
      "embedding_similarity": 0.974708,
      "structural_overlap": 0.06
    }
  ],
  "texts": [
    "## Part 1: Background\nThe field of geometry filtering relies heavily on low-rank matrix approximation techniques to efficiently estimate local and non-local features from point clouds and meshes. While these methods have demonstrated robustness in specific contexts, they often lack the ability to adapt to domain-specific constraints imposed by the underlying system. Simultaneously, the debate over whether learning requires memorization has shifted focus toward understanding the trade-offs between over-parameterization and generalization in image recognition tasks.\n\n## Part 2: Research Gap\nThere is a significant disconnect between the theoretical assumptions of geometry filtering and the empirical realities of constrained learning systems. Existing geometry filtering algorithms treat parameters as independent variables, ignoring the structural constraints that arise when a parameter is optimized to satisfy a system-level target. Conversely, research on data memorization often assumes idealized training sets without accounting for the dynamic, system-constrained optimization processes that characterize real-world learning environments.\n\n## Part 3: Proposed Direction\nWe propose a novel framework that integrates a system-constrained optimization mechanism into geometry filtering to address the lack of adaptability. Specifically, we will implement a parameter $X$ constrained by a system $Y$ to minimize a target $T$, where the algorithm converges when $X$ approaches the limit of constraint $Z$. This will be tested by applying this constrained optimization to a standard low-rank approximation algorithm and comparing its performance against un-constrained baselines on synthetic point cloud datasets where the system constraints mimic real-world geometric priors.\n\n## Part 4: Expected Contribution\nThis work aims to bridge the gap between geometric filtering and constrained learning by demonstrating how system-level constraints can be harnessed to improve the robustness of low-rank matrix approximation. By validating the proposed direction on synthetic point cloud datasets, we expect to show that incorporating system constraints leads to more stable and generalizable feature estimates, thereby offering a new theoretical and practical pathway for enhancing geometry filtering algorithms.",
    "## Part 1: Background\nRecent advancements in robotics have demonstrated that automatic differentiation (AD) combined with continuous sensitivity analysis is a powerful tool for learning dynamic models from data. Simultaneously, social network analysis has established that exploiting consistency theory can effectively model the propagation of hashtag adoption on platforms like Twitter. While both fields address complex, dynamic systems through rigorous mathematical frameworks, they operate in distinct domains: one focuses on physical dynamics and the other on social information spread.\n\n## Part 2: Research Gap\nDespite the shared algorithmic structure of optimizing constraints to minimize parameters, there is a significant lack of empirical evidence linking these two methodologies. Existing literature treats physical dynamics and social propagation as isolated problems, failing to identify if the structural holes between them\u2014specifically the duality of constraint minimization and parameter convergence\u2014can be leveraged to improve model robustness in hybrid systems. Furthermore, no study has yet proposed a unified framework to test whether consistency theory applied to social hashtags can enhance the stability of AD-based robot dynamics models.\n\n## Part 3: Proposed Direction\nWe propose a novel experimental framework that integrates constraint propagation from Twitter hashtag adoption into the sensitivity analysis of rigid body dynamics. Specifically, we will construct a synthetic dataset where the \"Target T\" represents a social hashtag spread governed by consistency rules, and we will apply these rules to constrain the optimization of a robot's parameters (Parameter X) to minimize Constraint Z. By running this agent to optimize Parameter X to minimize Constraint Z, where Target T converges under the rule that Parameter X must satisfy Constraint Z, we will directly test if the structural hole between cs.MS and cs.NA leads to more stable, data-efficient dynamic models.\n\n## Part 4: Expected Contribution\nThis research aims to bridge the gap between physical control theory and social network analysis by demonstrating that exploiting consistency theory for modeling hashtag adoption can serve as a robust prior for AD-based robot dynamics. The expected contribution is a validated structural hole between cs.MS and cs.NA that proves consistency-based propagation can reduce the variance in parameter estimation during continuous sensitivity analysis, thereby enabling robots to reason more effectively in dynamic environments with limited data.",
    "## Part 1: Background\nSingle-hidden layer feed forward neural networks (SLFNs) are widely used in pattern classification, but traditional iterative gradient-based learning algorithms suffer from slow convergence and poor performance. Conversely, hierarchical motion planning frameworks for quadrotors are popular for time efficiency but fail to properly handle non-static initial states in unknown environments. Despite the distinct challenges in neural network training and kinodynamic trajectory replanning, there is no established cross-domain structural hole connecting these two specific algorithmic bottlenecks.\n\n## Part 2: Research Gap\nThe primary gap lies in the lack of a unified theoretical framework that can bridge the slow convergence of SLFNs with the dynamic state constraints of quadrotor replanning. Existing studies treat these domains in isolation, ignoring that the optimization objective in one domain (minimizing error in classification) can be structurally analogous to the feasibility constraint in the other (ensuring state $X$ satisfies target $T$). Without this cross-domain insight, developing a generalizable, efficient algorithm for both SLFN regularization and quadrotor kinodynamic replanning remains an unsolved problem.\n\n## Part 3: Proposed Direction\nWe propose to develop a unified cross-domain structural hole model that transforms the parameter optimization of SLFNs into a kinodynamic replanning problem for quadrotors. Specifically, we will design a new algorithm where the parameters of the neural network are treated as the state of the system, and the regularization objective becomes the feasibility constraint for the quadrotor's trajectory. We will implement this by training a Gegenbauer NN with regularized weights to directly determine optimal parameters, then applying this logic to a quadrotor's path planning to ensure it satisfies the target state $T$ while minimizing the objective function of the system.\n\n## Part 4: Expected Contribution\nThis work will yield a novel cross-domain algorithm capable of simultaneously addressing the speed and performance limitations of SLFNs and the dynamic state issues in quadrotor motion planning. By formalizing the structural relationship between parameter optimization and kinodynamic feasibility, we expect to create a more efficient framework that reduces the computational burden of iterative learning in neural networks while ensuring robust autonomous flight in unknown environments. This approach offers a scalable solution for complex pattern classification and dynamic trajectory control tasks.",
    "## Part 1: Background\nAutomatic differentiation (AD) and continuous sensitivity analysis are foundational techniques for enabling robots to reason about dynamic environments, while spatiotemporal k-SVD dictionary learning provides robust methods for online multi-target tracking. Both fields rely on the ability to efficiently compute gradients and identify discriminative features across different domains. However, existing literature treats these methodologies in isolation, lacking a unified framework that explicitly bridges the gap between rigid body dynamics optimization and multi-target appearance discrimination.\n\n## Part 2: Research Gap\nThe current literature suffers from a domain-blind structural hole: while Agent A optimizes constraints for rigid body dynamics and Agent B optimizes parameters for multi-target tracking, there is no established mechanism to propagate updates or constraints between these distinct domains. Specifically, the lack of a shared algorithmic architecture prevents the transfer of learned parameters from one domain (e.g., tracking appearance) to optimize another (e.g., dynamic constraints), limiting the scalability and generalizability of intelligent robotic agents.\n\n## Part 3: Proposed Direction\nWe propose a unified structural hole bridging the gap by developing a shared algorithmic framework where Agent A propagates constraints from Target T to optimize Parameter X, while simultaneously allowing Agent B to propagate updates from Parameter X to refine Target T. This involves designing a domain-blind optimization loop that minimizes the discrepancy between the dynamic constraints and the discriminative tracking features, ensuring that updates in one domain directly inform the stability and adaptability of the other.\n\n## Part 4: Expected Contribution\nOur work will demonstrate a novel method for cross-domain parameter propagation, where updates from multi-target tracking can be effectively utilized to refine the constraints governing rigid body dynamics. This approach is expected to significantly improve the robustness of robots in dynamic environments by leveraging the discriminative power of tracking algorithms to stabilize complex physical interactions, thereby advancing the state of intelligent, physically-aware robotic control.",
    "## Part 1: Background\nAudio-visual scene-aware dialog systems (AVSD) and 3D human pose/shape recovery (SMPL) represent two distinct yet increasingly critical domains in intelligent systems. While AVSD challenges focus on multi-turn conversational understanding across video and audio modalities, current SMPL-based solutions often struggle to accurately predict complex 3D body geometries despite their widespread adoption. Both fields rely heavily on deep neural networks, yet they face unique computational and interpretational bottlenecks that limit their real-world applicability in dynamic and complex environments.\n\n## Part 2: Research Gap\nThe fundamental disconnect lies in the lack of unified algorithmic frameworks capable of bridging these disparate modalities. Existing approaches treat audio-visual generation and 3D shape reconstruction as isolated tasks, ignoring the potential for shared optimization principles. Furthermore, current methods fail to leverage structural holes between these domains to transfer knowledge effectively; for instance, while SMPL models excel in static pose estimation, they lack robust mechanisms to adapt to the dynamic, multi-turn conversational constraints found in AVSD, and vice versa.\n\n## Part 3: Proposed Direction\nWe propose a domain-blind agent architecture that optimizes a shared parameter $X$ to minimize a specific loss $Y$ while ensuring a target $Z$ converges under a constraint $W$. This agent will be trained to jointly optimize parameters across the SMPL body model and the AVSD dialogue context, effectively transferring structural knowledge from the 3D reconstruction domain to the conversational domain. Specifically, we will implement a multi-modal constraint solver where the agent iteratively updates parameters $X$ to minimize $Y$ (pose error) while enforcing $Z$ (dialogue coherence) under the constraint that $W$ (visual attention) is bounded by the SMPL shape prior. This approach will be validated through a novel benchmark that requires the agent to generate coherent dialogue responses based on 3D human poses derived from SMPL models.\n\n## Part 4: Expected Contribution\nThis research aims to establish a novel, domain-agnostic optimization framework that bridges the gap between 3D human reconstruction and conversational AI. By demonstrating how structural knowledge from SMPL can be leveraged to improve AVSD performance, we expect to provide a scalable solution for generating high-fidelity, context-aware dialogues from 3D human poses. The resulting framework will offer a new paradigm for cross-modal learning, potentially enabling more accurate and natural interactions in applications ranging from virtual avatars to immersive video games."
  ]
}